RJcalculator/__init__.py
RJcalculator-0.3.2.dist-info/LICENCE.txt
RJcalculator-0.3.2.dist-info/METADATA
RJcalculator-0.3.2.dist-info/WHEEL
RJcalculator-0.3.2.dist-info/top_level.txt
RJcalculator-0.3.2.dist-info/RECORD
